LICENSE
README.md
setup.py
linkedin_search_results/__init__.py
linkedin_search_results.egg-info/PKG-INFO
linkedin_search_results.egg-info/SOURCES.txt
linkedin_search_results.egg-info/dependency_links.txt
linkedin_search_results.egg-info/requires.txt
linkedin_search_results.egg-info/top_level.txt