Metadata-Version: 2.1
Name: linkedin-search-results
Version: 1.0.3
Summary: A python library to scrape linkedin search results
Home-page: UNKNOWN
Author: DataKund
Author-email: datakund@gmail.com
License: Apache License 2.0
Keywords: linkedin search results python bot_studio automation search scraper scrape
Platform: UNKNOWN
License-File: LICENSE
